CHANGES.txt
COPYRIGHT.txt
HISTORY.txt
LICENSE.txt
README.txt
TODO.txt
setup.cfg
setup.py
docs/Makefile
docs/api.rst
docs/authorintro.rst
docs/build_book
docs/changes.rst
docs/conf.py
docs/conventions.rst
docs/convert_images.sh
docs/copyright.rst
docs/designdefense.rst
docs/foreword.rst
docs/glossary.rst
docs/index.rst
docs/latexindex.rst
docs/layout_bookad.html
docs/whatsnew-1.1.rst
docs/whatsnew-1.2.rst
docs/whatsnew-1.3.rst
docs/zcml.rst
docs/.static/exclaim.png
docs/.static/exclaim_color.png
docs/.static/info.png
docs/.static/info_color.png
docs/.static/logo_hi.png
docs/.static/onebit_36.png
docs/.static/onebit_38.png
docs/.static/repoze.css
docs/.static/repoze_epub.css
docs/api/authentication.rst
docs/api/authorization.rst
docs/api/chameleon_text.rst
docs/api/chameleon_zpt.rst
docs/api/configuration.rst
docs/api/events.rst
docs/api/exceptions.rst
docs/api/i18n.rst
docs/api/interfaces.rst
docs/api/location.rst
docs/api/paster.rst
docs/api/renderers.rst
docs/api/request.rst
docs/api/router.rst
docs/api/scripting.rst
docs/api/security.rst
docs/api/settings.rst
docs/api/testing.rst
docs/api/threadlocal.rst
docs/api/traversal.rst
docs/api/url.rst
docs/api/view.rst
docs/api/wsgi.rst
docs/narr/configuration.rst
docs/narr/contextfinding.rst
docs/narr/environment.rst
docs/narr/events.rst
docs/narr/extending.rst
docs/narr/firstapp.rst
docs/narr/hooks.rst
docs/narr/hybrid.rst
docs/narr/i18n.rst
docs/narr/install.rst
docs/narr/introduction.rst
docs/narr/modelgraphtraverser.png
docs/narr/models.rst
docs/narr/project.png
docs/narr/project.rst
docs/narr/resources.rst
docs/narr/router.png
docs/narr/router.rst
docs/narr/security.rst
docs/narr/startup.rst
docs/narr/static.rst
docs/narr/templates.rst
docs/narr/threadlocals.rst
docs/narr/traversal.rst
docs/narr/unittesting.rst
docs/narr/urldispatch.rst
docs/narr/vhosting.rst
docs/narr/views.rst
docs/narr/webob.rst
docs/narr/zca.rst
docs/narr/MyProject/CHANGES.txt
docs/narr/MyProject/MyProject.ini
docs/narr/MyProject/README.txt
repoze.bfg.egg-info/PKG-INFO
repoze.bfg.egg-info/SOURCES.txt
repoze.bfg.egg-info/dependency_links.txt
repoze.bfg.egg-info/entry_points.txt
repoze.bfg.egg-info/namespace_packages.txt
repoze.bfg.egg-info/not-zip-safe
repoze.bfg.egg-info/requires.txt
repoze.bfg.egg-info/top_level.txt
