Metadata-Version: 1.0
Name: repoze.bfg
Version: 1.3
Summary: The repoze.bfg web application framework
Home-page: http://bfg.repoze.org
Author: Chris McDonough, Agendaless Consulting
Author-email: repoze-dev@lists.repoze.org
License: BSD-derived (http://www.repoze.org/LICENSE.txt)
Keywords: web wsgi bfg
Platform: UNKNOWN
Classifier: Intended Audience :: Developers
Classifier: Programming Language :: Python
Classifier: Framework :: BFG
Classifier: Topic :: Internet :: WWW/HTTP
Classifier: Topic :: Internet :: WWW/HTTP :: WSGI
Classifier: License :: Repoze Public License
